s2sphere/__init__.py
s2sphere/sphere.py
s2sphere-0.2.4.dist-info/DESCRIPTION.rst
s2sphere-0.2.4.dist-info/METADATA
s2sphere-0.2.4.dist-info/RECORD
s2sphere-0.2.4.dist-info/WHEEL
s2sphere-0.2.4.dist-info/metadata.json
s2sphere-0.2.4.dist-info/top_level.txt
