Metadata-Version: 1.1
Name: s2sphere
Version: 0.2.4
Summary: Python implementation of the S2 Geometry Library
Home-page: http://s2sphere.readthedocs.io
Author: Jonathan Gillham and contributors
Author-email: sven@sidewalklabs.com
License: MIT
Platform: UNKNOWN
Classifier: Development Status :: 4 - Beta
Classifier: Intended Audience :: Developers
Classifier: Intended Audience :: Science/Research
Classifier: Natural Language :: English
Classifier: License :: OSI Approved :: MIT License
Classifier: Operating System :: OS Independent
Classifier: Programming Language :: Python :: 3
Classifier: Programming Language :: Python :: 3.5
Classifier: Programming Language :: Python :: 3.4
Classifier: Programming Language :: Python :: 2
Classifier: Programming Language :: Python :: 2.7
